django_crispy_tableselect/__init__.py
django_crispy_tableselect/columns.py
django_crispy_tableselect/helpers.py
django_crispy_tableselect/layout.py
django_crispy_tableselect/mixins.py
django_crispy_tableselect/locale/nl/LC_MESSAGES/django.mo
django_crispy_tableselect/locale/nl/LC_MESSAGES/django.po
django_crispy_tableselect/static/django_crispy_tableselect/tableselect.js
django_crispy_tableselect/templates/django_crispy_tableselect/checkbox_column_header.html
django_crispy_tableselect/templates/django_crispy_tableselect/narrator.html
django_crispy_tableselect/templates/django_crispy_tableselect/select_all_checkbox.html
django_crispy_tableselect/templates/django_crispy_tableselect/table_select.html
django_crispy_tableselect-0.1.0.dist-info/METADATA
django_crispy_tableselect-0.1.0.dist-info/WHEEL
django_crispy_tableselect-0.1.0.dist-info/licenses/LICENSE
django_crispy_tableselect-0.1.0.dist-info/RECORD
