Metadata-Version: 2.3
Name: django-crispy-tableselect
Version: 0.1.0
Summary: Crispy layout object for selecting rows in a table
Project-URL: Changelog, https://github.com/Stormbase/django-crispy-tableselect/blob/main/CHANGELOG.md
Project-URL: Issues, https://github.com/Stormbase/django-crispy-tableselect/issues
Project-URL: Source, https://github.com/Stormbase/django-crispy-tableselect
Author-email: "Storm B. Heg" <storm@stormbase.digital>
License-Expression: MIT
License-File: LICENSE
Keywords: crispy-forms,django
Classifier: Development Status :: 4 - Beta
Classifier: Environment :: Web Environment
Classifier: Framework :: Django
Classifier: Framework :: Django :: 4.2
Classifier: Framework :: Django :: 5.0
Classifier: Intended Audience :: Developers
Classifier: License :: OSI Approved :: MIT License
Classifier: Operating System :: OS Independent
Classifier: Programming Language :: Python
Classifier: Programming Language :: Python :: 3
Classifier: Programming Language :: Python :: 3.9
Classifier: Programming Language :: Python :: 3.10
Classifier: Programming Language :: Python :: 3.11
Classifier: Programming Language :: Python :: 3.12
Requires-Python: >=3.9
Requires-Dist: django-crispy-forms<3.0,>=2.0
Requires-Dist: django-tables2<3,>=2.4
Requires-Dist: django>=4.2
